awesomediegopackage/__init__.py
awesomediegopackage/__main__.py
awesomediegopackage/advanced_arithmetic.py
awesomediegopackage/basic_arithmetic.py
awesomediegopackage-0.0.1.dist-info/LICENSE.md
awesomediegopackage-0.0.1.dist-info/METADATA
awesomediegopackage-0.0.1.dist-info/WHEEL
awesomediegopackage-0.0.1.dist-info/top_level.txt
awesomediegopackage-0.0.1.dist-info/RECORD
