Metadata-Version: 2.1
Name: awesomediegopackage
Version: 0.0.1
Summary: My first (useless) package
Home-page: https://github.com/DiegoStucchi/DiegosFirstPackageGit
Author: Diego Stucchi (test)
Author-email: stucchidiego1994@gmail.com
License: MIT
Keywords: python,first package
Platform: UNKNOWN
Classifier: Development Status :: 1 - Planning
Classifier: Intended Audience :: Developers
Classifier: Programming Language :: Python :: 3
Classifier: Operating System :: Unix
Classifier: Operating System :: MacOS :: MacOS X
Classifier: Operating System :: Microsoft :: Windows
